frechetdist.py
frechetdist-0.6.dist-info/LICENSE
frechetdist-0.6.dist-info/METADATA
frechetdist-0.6.dist-info/WHEEL
frechetdist-0.6.dist-info/top_level.txt
frechetdist-0.6.dist-info/RECORD
