Metadata-Version: 2.1
Name: frechetdist
Version: 0.6
Summary: Calculate discrete Frechet distance
Home-page: https://github.com/spiros/discrete_frechet
Author: Spiros Denaxas
Author-email: s.denaxas@gmail.com
License: Apache License 2.0
Platform: UNKNOWN
Classifier: Programming Language :: Python :: 3
Classifier: Operating System :: OS Independent
